.DS_Store
ghgforcing/__init__.py
ghgforcing/ghgforcing.py
ghgforcing-0.1.7.1.dist-info/DESCRIPTION.rst
ghgforcing-0.1.7.1.dist-info/METADATA
ghgforcing-0.1.7.1.dist-info/RECORD
ghgforcing-0.1.7.1.dist-info/WHEEL
ghgforcing-0.1.7.1.dist-info/metadata.json
ghgforcing-0.1.7.1.dist-info/top_level.txt
