Metadata-Version: 2.0
Name: ghgforcing
Version: 0.1.7.1
Summary: Calculate radiative forcing from GHG emissions
Home-page: https://github.com/gschivley/ghgforcing
Author: Greg Schivley
Author-email: greg.schivley@gmail.com
License: MIT
Platform: UNKNOWN
Requires-Dist: numpy
Requires-Dist: pandas
Requires-Dist: scipy
